quantel/__init__.py
quantel/exceptions.py
tests/__init__.py
tests/test_quantel_exceptions.py
tests/test_quantel_properties.py
quantel-0.4.dist-info/METADATA
quantel-0.4.dist-info/WHEEL
quantel-0.4.dist-info/top_level.txt
quantel-0.4.dist-info/RECORD
