Metadata-Version: 2.1
Name: quantel
Version: 0.4
Summary: Interact with the Quantel Finance API
Home-page: https://quantel.io
Author: Guy M
Author-email: guy@quantel.io
License: MIT
Project-URL: Documentation, http://links.quantel.io/python-docs
Project-URL: Source, https://github.com/ratherbland/quantel
Keywords: quantel,finance,stocks,mutual funds,etfs,insider transactions,financial data
Platform: UNKNOWN
Classifier: Programming Language :: Python :: 3.6
Classifier: Programming Language :: Python :: 3.7
Classifier: Programming Language :: Python :: 3.8
Classifier: Programming Language :: Python :: 3.9
Classifier: Intended Audience :: Financial and Insurance Industry
Classifier: Operating System :: OS Independent
